yashas_maths/__init__.py
yashas_maths/addsub.py
yashas_maths/expo.py
yashas_maths/modfloor.py
yashas_maths/muldiv.py
yashas_maths-0.0.1.dist-info/METADATA
yashas_maths-0.0.1.dist-info/WHEEL
yashas_maths-0.0.1.dist-info/top_level.txt
yashas_maths-0.0.1.dist-info/RECORD
